PISO.v
/*	Joanna Mazer
	EE 371 Peckol Winter 2016
	Project 3: Extending a Microprocessor
	PISO.v
	
	This verilog module functions as a parallel in, serial out
	shift register. The 10 bit data will be loaded into the shift
	register, then when the load signal is not enabled, the data
	will be fed to the output one bit at a time on the posedge 
	of the clock signal.
*/

module PISO(clk, reset, data_in, load_n, data_out); // Parallel in -> Serial Out (10 bits)

	input 		clk, reset, load_n;
	input [9:0] data_in;
	output 		data_out;

	reg [9:0] 	Q_out;
	reg 		serial_out;

	always @(posedge clk or posedge reset) begin
		if (reset) begin
			Q_out <= 10'b0000000000;
		end
		else if (load_n) begin   // shift
			serial_out <= Q_out[0];
			Q_out[0] <= Q_out[1];
			Q_out[1] <= Q_out[2];
			Q_out[2] <= Q_out[3];
			Q_out[3] <= Q_out[4];
			Q_out[4] <= Q_out[5];
			Q_out[5] <= Q_out[6];
			Q_out[6] <= Q_out[7];
			Q_out[7] <= Q_out[8];
			Q_out[8] <= Q_out[9];
			Q_out[9] <= 1'b1;
		end
		else begin				// load
			Q_out <= data_in;
		end
	end

	assign data_out = serial_out; 

endmodule

PISO_testbench.v
`include "PISO.v"

module PISO_testbench;
	// connect the two modules
	wire 		clk, reset, data_out, load_n;
	wire [9:0] 	data_in;
	
	// declare an instance of the module
	PISO PISO_test(clk, reset, data_in, load_n, data_out);

	// declare an instance of the Tester module
	Tester test1(clk, reset, data_in, load_n, data_out);
	
	// file specifications for gtkwave
	initial
		begin
		// dump file is for dumping all the variables in a simulation
		$dumpfile("PISO.vcd");
		
		// dumps all the variables in module myDesign and below
		// but not modules instantiated in myDesign into the dump file.
		$dumpvars(1, PISO_test);
		end

endmodule

module Tester (clk, reset, data_in, load_n, data_out);
	input 		data_out;
	output 		clk, reset, load_n;
	output 		[9:0] data_in;

	reg 		clk, reset, load_n;
	reg 		[9:0] data_in;
	
	parameter stimDelay = 10;
	
	initial begin 
		$display("\t\t clk reset data_in load_n \t data_out \t Time");
		$monitor("\t\t %b \t %b \t %b \t %b \t %b", clk, reset, data_in, load_n, data_out, $time);
	end
	
	always #stimDelay clk = ~clk;
	
	initial begin // Stimulus 
		#(2*stimDelay) clk = 1'b0; reset = 1'b0; data_in = 10'b0100101111; load_n = 1'b0;
		#(2*stimDelay) reset = 1'b1;	// reset the system
		#(2*stimDelay) reset = 1'b0;
		#(2*stimDelay) data_in = 10'b0100101111; load_n = 1'b0;
		#(2*stimDelay);
		#(2*stimDelay) load_n = 1'b1;

		#(20*stimDelay); 				// needed to see END of simulation
		$finish; 						// finish simulation
	end

endmodule

PISO.vcd
$date
	Tue Feb 16 13:24:59 2016
$end
$version
	Icarus Verilog
$end
$timescale
	1s
$end
$scope module PISO_testbench $end
$scope module PISO_test $end
$var wire 1 ! clk $end
$var wire 10 " data_in [9:0] $end
$var wire 1 # data_out $end
$var wire 1 $ load_n $end
$var wire 1 % reset $end
$var reg 10 & Q_out [9:0] $end
$var reg 1 ' serial_out $end
$upscope $end
$upscope $end
$enddefinitions $end
#0
$dumpvars
x'
bx &
x%
x$
x#
bx "
x!
$end
#20
b100101111 &
0$
b100101111 "
0%
1!
#30
0!
#40
b0 &
1!
1%
#50
0!
#60
b100101111 &
1!
0%
#70
0!
#80
1!
#90
0!
#100
1!
#110
0!
#120
b1010010111 &
1'
1#
1!
1$
#130
0!
#140
b1101001011 &
1!
#150
0!
#160
b1110100101 &
1!
#170
0!
#180
b1111010010 &
1!
#190
0!
#200
b1111101001 &
0'
0#
1!
#210
0!
#220
b1111110100 &
1'
1#
1!
#230
0!
#240
b1111111010 &
0'
0#
1!
#250
0!
#260
b1111111101 &
1!
#270
0!
#280
b1111111110 &
1'
1#
1!
#290
0!
#300
b1111111111 &
0'
0#
1!
#310
0!
#320
b1111111111 &
1'
1#
1!
